MANIFEST.in
README
setup.py
pymirna/Result.db
pymirna/Result.log
pymirna/__init__.py
pymirna/main.py
pymirna/path
pymirna.egg-info/PKG-INFO
pymirna.egg-info/SOURCES.txt
pymirna.egg-info/dependency_links.txt
pymirna.egg-info/requires.txt
pymirna.egg-info/top_level.txt
pymirna/Datasets/EST_test.fasta
pymirna/Datasets/let7.fasta
pymirna/Examples/seqio_example.py
pymirna/UI/.pmi
pymirna/UI/CutadaptUI.py
pymirna/UI/Discovery.py
pymirna/UI/DiscoveryToolBlock.py
pymirna/UI/FastxUI.py
pymirna/UI/FloatingWidget.py
pymirna/UI/GlobalVariable.py
pymirna/UI/MainPage.py
pymirna/UI/PreProcessUI.py
pymirna/UI/PreProcessingToolBlock.py
pymirna/UI/SelectInputDialog.py
pymirna/UI/SettingBlock.py
pymirna/UI/TargetPrediction.py
pymirna/UI/TargetPredictionToolBlock.py
pymirna/UI/ToolBlock.py
pymirna/UI/WorkflowUI.py
pymirna/UI/__init__.py
pymirna/UI/fileViewer.py
pymirna/UI/mComboBox.py
pymirna/UI/mTextEdit.py
pymirna/UI/mTreeWidgetItem.py
pymirna/UI/miRandaUI.py
pymirna/Utility/FileReader.py
pymirna/Utility/ProjectUtility.py
pymirna/Utility/__init__.py