Metadata-Version: 1.0
Name: pymirna
Version: 0.1.0
Summary: pymirna: The Pythonic microRNA Library
Home-page: UNKNOWN
Author: K. Somboonviwat
Author-email: kulwadee.a@gmail.com
License: MIT
Platform: UNKNOWN
